tpu_mlir/__init__.py
tpu_mlir/entry.py
tpu_mlir/entryconfig.py
tpu_mlir/PplBackend/.md5
tpu_mlir/PplBackend/CMakeLists.txt
tpu_mlir/PplBackend/Dynkernel.cmake
tpu_mlir/PplBackend/build.sh
tpu_mlir/PplBackend/download_toolchain.sh
tpu_mlir/PplBackend/examples/avg_pool2d.pl
tpu_mlir/PplBackend/examples/avg_pool_2d_local.pl
tpu_mlir/PplBackend/examples/conv.cpp
tpu_mlir/PplBackend/examples/conv2d.pl
tpu_mlir/PplBackend/examples/pooling.cpp
tpu_mlir/PplBackend/examples/pooling_local.cpp
tpu_mlir/PplBackend/examples/rms_norm.cpp
tpu_mlir/PplBackend/examples/rms_norm.pl
tpu_mlir/PplBackend/examples/softmax.cpp
tpu_mlir/PplBackend/examples/softmax.pl
tpu_mlir/PplBackend/include/helper.h
tpu_mlir/PplBackend/include/local_base.h
tpu_mlir/PplBackend/include/ppl_dyn_fw.h
tpu_mlir/PplBackend/include/ppl_static_host.h
tpu_mlir/PplBackend/src/add_const_fp.pl
tpu_mlir/PplBackend/src/add_const_fp_api.cpp
tpu_mlir/PplBackend/src/add_const_fp_local.pl
tpu_mlir/PplBackend/src/add_const_fp_tile.cpp
tpu_mlir/PplBackend/src/correlation.cpp
tpu_mlir/PplBackend/src/correlation_fp.pl
tpu_mlir/PplBackend/src/fattention_api.cpp
tpu_mlir/PplBackend/src/fattention_bf16.pl
tpu_mlir/PplBackend/src/fattention_fp16.pl
tpu_mlir/PplBackend/src/fattention_tile.cpp
tpu_mlir/PplBackend/src/fattention_v2.pl
tpu_mlir/PplBackend/src/interp.cpp
tpu_mlir/PplBackend/src/interp_linear.pl
tpu_mlir/PplBackend/src/interp_nearest.pl
tpu_mlir/PplBackend/src/selective_scan.cpp
tpu_mlir/PplBackend/src/selective_scan.pl
tpu_mlir/PplBackend/src_dyn/add_const_ctrl.c
tpu_mlir/PplBackend/src_dyn/dyn_layer_ctrl.c
tpu_mlir/PplBackend/src_dyn/fattention_ctrl.c
tpu_mlir/PplBackend/src_dyn/interp_ctr.c
tpu_mlir/bin/cvimodel_debug
tpu_mlir/bin/model_tool
tpu_mlir/bin/tpuc-opt
tpu_mlir/bin/tpuc-tool
tpu_mlir/customlayer/CMakeLists.txt
tpu_mlir/customlayer/envsetup.sh
tpu_mlir/customlayer/register_ops.cmake
tpu_mlir/customlayer/PplBackend/include/helper.h
tpu_mlir/customlayer/PplBackend/src/add_const_fp.pl
tpu_mlir-1.26.dist-info/licenses/LICENSE
tpu_mlir-1.26.dist-info/METADATA
tpu_mlir-1.26.dist-info/WHEEL
tpu_mlir-1.26.dist-info/entry_points.txt
tpu_mlir-1.26.dist-info/top_level.txt
tpu_mlir-1.26.dist-info/RECORD
