Metadata-Version: 2.4
Name: tpu_mlir
Version: 1.26
Summary: Machine learning compiler based on MLIR for TPU v1.26-gafbae3b-20251229
Home-page: https://tpumlir.org/
Author: TPU-MLIR Team
Author-email: 
License: 2-Clause BSD
Keywords: python3.10,unbuntu22.04,linux,tpu-mlir
Platform: unbuntu22.04
Classifier: Intended Audience :: Developers
Classifier: Programming Language :: Python :: 3.10
Classifier: Topic :: Software Development
Requires-Python: >=3.10,<3.11
License-File: LICENSE
Requires-Dist: numpy==1.24.3
Requires-Dist: scipy==1.11.1
Requires-Dist: tqdm==4.65.0
Requires-Dist: Pillow==10.0.0
Requires-Dist: plotly==5.15.0
Requires-Dist: opencv-python-headless==4.8.0.74
Requires-Dist: protobuf==3.20.3
Requires-Dist: graphviz==0.20.1
Requires-Dist: pycocotools==2.0.6
Requires-Dist: scikit-image==0.21.0
Requires-Dist: transformers==4.51.1
Requires-Dist: scikit-learn==1.6.1
Requires-Dist: onnxruntime_extensions==0.14.0
Requires-Dist: pandas==2.0.3
Provides-Extra: all
Requires-Dist: torch==2.1.0; extra == "all"
Requires-Dist: torchvision==0.16.0; extra == "all"
Requires-Dist: onnx==1.14.1; extra == "all"
Requires-Dist: onnxruntime==1.16.3; extra == "all"
Requires-Dist: onnxsim==0.4.17; extra == "all"
Requires-Dist: six==1.16.0; extra == "all"
Requires-Dist: tf2onnx==1.8.4; extra == "all"
Requires-Dist: paddlepaddle==2.5.0; extra == "all"
Requires-Dist: paddle2onnx==1.0.8; extra == "all"
Requires-Dist: astunparse==1.6.3; extra == "all"
Requires-Dist: flatbuffers==24.12.23; extra == "all"
Requires-Dist: setuptools==59.6.0; extra == "all"
Requires-Dist: tensorboard==2.13.0; extra == "all"
Provides-Extra: torch
Requires-Dist: torch==2.1.0; extra == "torch"
Requires-Dist: torchvision==0.16.0; extra == "torch"
Provides-Extra: onnx
Requires-Dist: onnx==1.14.1; extra == "onnx"
Requires-Dist: onnxruntime==1.16.3; extra == "onnx"
Requires-Dist: onnxsim==0.4.17; extra == "onnx"
Provides-Extra: caffe
Requires-Dist: six==1.16.0; extra == "caffe"
Provides-Extra: tensorflow
Requires-Dist: tf2onnx==1.8.4; extra == "tensorflow"
Provides-Extra: paddle
Requires-Dist: paddlepaddle==2.5.0; extra == "paddle"
Requires-Dist: paddle2onnx==1.0.8; extra == "paddle"
Dynamic: author
Dynamic: classifier
Dynamic: description
Dynamic: description-content-type
Dynamic: home-page
Dynamic: keywords
Dynamic: license
Dynamic: license-file
Dynamic: platform
Dynamic: provides-extra
Dynamic: requires-dist
Dynamic: requires-python
Dynamic: summary
